VIPER_LIMS/VIPER_Installer.py
VIPER_LIMS/__init__.py
VIPER_LIMS-0.1.3.dist-info/LICENSE
VIPER_LIMS-0.1.3.dist-info/METADATA
VIPER_LIMS-0.1.3.dist-info/WHEEL
VIPER_LIMS-0.1.3.dist-info/top_level.txt
VIPER_LIMS-0.1.3.dist-info/RECORD
