Metadata-Version: 2.1
Name: VIPER-LIMS
Version: 0.1.3
Summary: A free and open-source LIMS software with scriptable modules.
Home-page: https://github.com/JackLawrenceCRISPR/VIPER-LIMS
Author: VIPER-LIMS (Jack Lawrence)
Author-email: <JackLawrenceCRISPR@gmail.com>
License: MIT
Keywords: python,installer,lims,science
Classifier: Development Status :: 2 - Pre-Alpha
Classifier: Intended Audience :: Developers
Classifier: Intended Audience :: Science/Research
Classifier: Intended Audience :: System Administrators
Classifier: Intended Audience :: End Users/Desktop
Classifier: Framework :: Flask
Classifier: Programming Language :: Python :: 3
Classifier: Operating System :: Unix
Classifier: Operating System :: MacOS :: MacOS X
Classifier: Operating System :: Microsoft :: Windows
Classifier: Operating System :: Android
Classifier: License :: OSI Approved :: MIT License
Classifier: Natural Language :: English
Classifier: Topic :: Scientific/Engineering
Classifier: Topic :: Database
Requires: requests
Requires-Python: >=3.7
License-File: LICENSE
